pfDevTools/CoreConfig.py
pfDevTools/OpenFPGACore.py
pfDevTools/Package.py
pfDevTools/Paths.py
pfDevTools/SConsEnv.py
pfDevTools/__about__.py
pfDevTools/__init__.py
pfDevTools/PfCommand/Clean.py
pfDevTools/PfCommand/Clone.py
pfDevTools/PfCommand/Command.py
pfDevTools/PfCommand/Convert.py
pfDevTools/PfCommand/Delete.py
pfDevTools/PfCommand/DryRun.py
pfDevTools/PfCommand/Eject.py
pfDevTools/PfCommand/Install.py
pfDevTools/PfCommand/Make.py
pfDevTools/PfCommand/PfCommand.py
pfDevTools/PfCommand/Program.py
pfDevTools/PfCommand/Qfs.py
pfDevTools/PfCommand/Reverse.py
pfDevTools/PfCommand/__main__.py
pf_dev_tools-2.2.0.dist-info/METADATA
pf_dev_tools-2.2.0.dist-info/WHEEL
pf_dev_tools-2.2.0.dist-info/entry_points.txt
pf_dev_tools-2.2.0.dist-info/licenses/LICENSE
pf_dev_tools-2.2.0.dist-info/RECORD
