Metadata-Version: 2.4
Name: pf-dev-tools
Version: 2.2.0
Summary: A collection of tools for Project Freedom projects
Project-URL: Homepage, https://code.malenfant.net/didier/pfDevTools
Project-URL: Documentation, https://code.malenfant.net/didier/pfDevTools#readme
Project-URL: Bug Tracker, https://code.malenfant.net/didier/pfDevTools/issues
Project-URL: Source Code, https://code.malenfant.net/didier/pfDevTools
Author-email: Didier Malenfant <didier@malenfant.net>
License-Expression: GPL-3.0-or-later
License-File: LICENSE
Keywords: ProjectFreedom,analoguepocket,fpga,openFPGA
Classifier: Development Status :: 5 - Production/Stable
Classifier: Programming Language :: Python
Classifier: Programming Language :: Python :: 3.10
Classifier: Programming Language :: Python :: Implementation :: CPython
Classifier: Programming Language :: Python :: Implementation :: PyPy
Requires-Python: >=3.10
Requires-Dist: dm-py-utilities>=2.2.0
Requires-Dist: pillow
Requires-Dist: scons
Requires-Dist: semver>=3
Requires-Dist: tomli>=1.1.0; python_version < '3.11'
